ms21xx_firmware/__init__.py
ms21xx_firmware/generate.py
ms21xx_firmware/py.typed
ms21xx_firmware/firmwares/ms2109.bin
ms21xx_firmware/firmwares/ms2130.bin
ms21xx_firmware-1.0.1.dist-info/LICENSE
ms21xx_firmware-1.0.1.dist-info/METADATA
ms21xx_firmware-1.0.1.dist-info/WHEEL
ms21xx_firmware-1.0.1.dist-info/entry_points.txt
ms21xx_firmware-1.0.1.dist-info/top_level.txt
ms21xx_firmware-1.0.1.dist-info/RECORD
