Metadata-Version: 2.1
Name: ms21xx-firmware
Version: 1.0.1
Summary: Tool to generate ms21xx firmware with custom VID, PID, EDID, descriptors and serial number
Author-email: Pradish Bijukchhe <pradish@sandbox.com.np>
License: Copyright (c) 2018 The Python Packaging Authority
Project-URL: Homepage, https://github.com/sandbox-pokhara/ms21xx-firmware
Project-URL: Issues, https://github.com/sandbox-pokhara/ms21xx-firmware/issues
Classifier: Programming Language :: Python :: 3
Requires-Python: >=3
License-File: LICENSE
